setup.py
odoo/addons/cooperator_api_somconnexio/CHANGELOG.md
odoo/addons/cooperator_api_somconnexio/README.rst
odoo/addons/cooperator_api_somconnexio/__init__.py
odoo/addons/cooperator_api_somconnexio/__manifest__.py
odoo/addons/cooperator_api_somconnexio/services/__init__.py
odoo/addons/cooperator_api_somconnexio/services/coop_agreement_service.py
odoo/addons/cooperator_api_somconnexio/services/crm_lead_service.py
odoo/addons/cooperator_api_somconnexio/services/discovery_channel_service.py
odoo/addons/cooperator_api_somconnexio/services/product_catalog_service.py
odoo/addons/cooperator_api_somconnexio/services/res_partner_process.py
odoo/addons/cooperator_api_somconnexio/services/res_partner_public_process.py
odoo/addons/cooperator_api_somconnexio/services/res_partner_public_service.py
odoo/addons/cooperator_api_somconnexio/services/res_partner_service.py
odoo/addons/cooperator_api_somconnexio/services/schemas.py
odoo/addons/cooperator_api_somconnexio/services/subscription_request_process.py
odoo/addons/cooperator_api_somconnexio/services/subscription_request_service.py
odoo/addons/cooperator_api_somconnexio/tests/__init__.py
odoo/addons/cooperator_api_somconnexio/tests/services/__init__.py
odoo/addons/cooperator_api_somconnexio/tests/services/test_coop_agreement_service.py
odoo/addons/cooperator_api_somconnexio/tests/services/test_crm_lead_service.py
odoo/addons/cooperator_api_somconnexio/tests/services/test_discovery_channel_service.py
odoo/addons/cooperator_api_somconnexio/tests/services/test_product_catalog_service.py
odoo/addons/cooperator_api_somconnexio/tests/services/test_res_partner_public_service.py
odoo/addons/cooperator_api_somconnexio/tests/services/test_res_partner_service.py
odoo/addons/cooperator_api_somconnexio/tests/services/test_subscription_request_service.py
odoo_addon_cooperator_api_somconnexio.egg-info/PKG-INFO
odoo_addon_cooperator_api_somconnexio.egg-info/SOURCES.txt
odoo_addon_cooperator_api_somconnexio.egg-info/dependency_links.txt
odoo_addon_cooperator_api_somconnexio.egg-info/not-zip-safe
odoo_addon_cooperator_api_somconnexio.egg-info/requires.txt
odoo_addon_cooperator_api_somconnexio.egg-info/top_level.txt