Metadata-Version: 2.4
Name: odoo-addon-cooperator_api_somconnexio
Version: 16.0.1.1.2
Summary: Expose a REST API to integrate cooperators and sponsorship to Som Connexió partner structure.
Home-page: https://git.coopdevs.org/coopdevs/som-connexio/odoo/odoo-somconnexio
Author: Som Connexió SCCL, Coopdevs Treball SCCL
License: AGPL-3
Classifier: Programming Language :: Python
Classifier: Framework :: Odoo
Classifier: Framework :: Odoo :: 16.0
Classifier: License :: OSI Approved :: GNU Affero General Public License v3
Requires-Python: >=3.10
Requires-Dist: odoo-addon-base_rest_somconnexio<16.1dev,>=16.0dev
Requires-Dist: odoo-addon-cooperator_somconnexio<16.1dev,>=16.0dev
Requires-Dist: odoo-addon-crm_lead_api_somconnexio<16.1dev,>=16.0dev
Requires-Dist: odoo-addon-res_partner_api_somconnexio<16.1dev,>=16.0dev
Requires-Dist: odoo<16.1dev,>=16.0a
Requires-Dist: python-stdnum
Dynamic: author
Dynamic: classifier
Dynamic: description
Dynamic: home-page
Dynamic: license
Dynamic: requires-dist
Dynamic: requires-python
Dynamic: summary
